{
  "name": "BRAZE",
  "displayName": "Braze",
  "config": {
    "isAudienceSupported": true,
    "supportsVisualMapper": true,
    "transformAt": "router",
    "transformAtV1": "router",
    "saveDestinationResponse": true,
    "includeKeys": [
      "appKey",
      "dataCenter",
      "trackAnonymousUser",
      "enableSubscriptionGroupInGroupCall",
      "enableBrazeLogging",
      "enableNestedArrayOperations",
      "supportDedup",
      "blacklistedEvents",
      "whitelistedEvents",
      "oneTrustCookieCategories",
      "eventFilteringOption"
    ],
    "excludeKeys": [],
    "supportedSourceTypes": [
      "android",
      "ios",
      "web",
      "unity",
      "amp",
      "cloud",
      "warehouse",
      "reactnative",
      "flutter",
      "cordova"
    ],
    "supportedMessageTypes": ["group", "identify", "page", "screen", "track"],
    "destConfig": {
      "defaultConfig": [
        "appKey",
        "dataCenter",
        "restApiKey",
        "trackAnonymousUser",
        "enableSubscriptionGroupInGroupCall",
        "enableNestedArrayOperations",
        "deduplicationEnabled",
        "blacklistedEvents",
        "trackAnonymousUser",
        "whitelistedEvents",
        "eventFilteringOption",
        "oneTrustCookieCategories"
      ],
      "android": ["useNativeSDK", "supportDedup"],
      "ios": ["useNativeSDK", "supportDedup"],
      "reactnative": ["useNativeSDK"],
      "flutter": ["useNativeSDK"],
      "web": ["useNativeSDK", "supportDedup", "enableBrazeLogging"]
    },
    "secretKeys": ["restApiKey"]
  }
}
