{
  "name": "WEBENGAGE",
  "displayName": "WebEngage",
  "config": {
    "transformAt": "processor",
    "transformAtV1": "processor",
    "saveDestinationResponse": true,
    "includeKeys": [
      "licenseCode",
      "dataCentre",
      "hashEmail",
      "hashPhone",
      "oneTrustCookieCategories"
    ],
    "excludeKeys": [],
    "supportedSourceTypes": [
      "web",
      "cloud",
      "mobile",
      "android",
      "ios",
      "unity",
      "amp",
      "warehouse",
      "reactnative",
      "flutter",
      "cordova",
      "shopify"
    ],
    "supportedConnectionModes": {
      "web": ["cloud", "device"]
    },
    "supportedMessageTypes": ["identify", "track", "page", "screen"],
    "destConfig": {
      "defaultConfig": ["licenseCode", "apiKey", "dataCenter"],
      "web": ["hashEmail", "hashPhone", "oneTrustCookieCategories"]
    }
  }
}
