{
  "name": "LEMNISK",
  "displayName": "Lemnisk Marketing Automation",
  "config": {
    "transformAt": "processor",
    "transformAtV1": "processor",
    "saveDestinationResponse": true,
    "includeKeys": [
      "apiKey",
      "passKey",
      "cloudMode",
      "diapi",
      "pl",
      "diapiWriteKey",
      "plWriteKey",
      "srcId",
      "sdkWriteKey",
      "accountId",
      "whitelistedEvents",
      "blacklistedEvents",
      "eventFilteringOption"
    ],
    "excludeKeys": [],
    "supportedSourceTypes": [
      "android",
      "ios",
      "web",
      "unity",
      "amp",
      "cloud",
      "reactnative",
      "flutter",
      "cordova",
      "warehouse"
    ],
    "supportedMessageTypes": ["track", "identify", "page"],
    "destConfig": {
      "defaultConfig": [
        "apiKey",
        "passKey",
        "cloudMode",
        "diapi",
        "pl",
        "diapiWriteKey",
        "sdkWriteKey",
        "accountId",
        "plWriteKey",
        "srcId",
        "whitelistedEvents",
        "blacklistedEvents",
        "eventFilteringOption"
      ],
      "web": ["useNativeSDK", "oneTrustCookieCategories"]
    },
    "secretKeys": ["apiKey", "passKey", "plWriteKey", "diapiWriteKey", "sdkWriteKey"]
  }
}
