{
  "configSchema": {
    "$schema": "http://json-schema.org/draft-07/schema#",
    "required": ["appId"],
    "type": "object",
    "properties": {
      "appId": {
        "type": "string",
        "pattern": "(^\\{\\{.*\\|\\|(.*)\\}\\}$)|(^env[.].+)|^(.{1,100})$"
      },
      "emailDeviceType": {
        "type": "boolean",
        "default": false
      },
      "smsDeviceType": {
        "type": "boolean",
        "default": false
      },
      "eventAsTags": {
        "type": "boolean",
        "default": false
      },
      "allowedProperties": {
        "type": "array",
        "items": {
          "type": "object",
          "properties": {
            "propertyName": {
              "type": "string",
              "pattern": "(^\\{\\{.*\\|\\|(.*)\\}\\}$)|(^env[.].+)|^(.{0,100})$"
            }
          }
        }
      },
      "oneTrustCookieCategories": {
        "type": "array",
        "items": {
          "type": "object",
          "properties": {
            "oneTrustCookieCategory": {
              "type": "string",
              "pattern": "(^\\{\\{.*\\|\\|(.*)\\}\\}$)|(^env[.].+)|^(.{0,100})$"
            }
          }
        }
      }
    }
  }
}
