{
  "name": "LEANPLUM",
  "displayName": "Leanplum",
  "config": {
    "transformAt": "processor",
    "transformAtV1": "processor",
    "saveDestinationResponse": true,
    "includeKeys": ["applicationId", "clientKey", "isDevelop", "useNativeSDKToSend"],
    "excludeKeys": [],
    "supportedSourceTypes": ["android", "ios", "web", "unity", "amp", "cloud", "warehouse", "reactnative", "flutter", "cordova"],
    "supportedMessageTypes": ["identify", "page", "screen", "track"],
    "destConfig": { "defaultConfig": ["applicationId", "clientKey", "isDevelop"], "android": ["useNativeSDK", "useNativeSDKToSend"], "ios": ["useNativeSDK", "useNativeSDKToSend"] },
    "secretKeys": ["clientKey"]
  }
}
