{
  "name": "FULLSTORY",
  "displayName": "Fullstory",
  "config": {
    "cdkV2Enabled": true,
    "transformAtV1": "processor",
    "saveDestinationResponse": true,
    "includeKeys": [
      "fs_debug_mode",
      "fs_org",
      "fs_host",
      "blacklistedEvents",
      "whitelistedEvents",
      "oneTrustCookieCategories",
      "eventFilteringOption",
      "consentManagement",
      "ketchConsentPurposes"
    ],
    "excludeKeys": [],
    "supportedSourceTypes": [
      "web",
      "android",
      "androidKotlin",
      "ios",
      "iosSwift",
      "unity",
      "amp",
      "cloud",
      "warehouse",
      "reactnative",
      "flutter",
      "cordova",
      "shopify"
    ],
    "supportedConnectionModes": {
      "android": ["cloud", "device"],
      "androidKotlin": ["cloud"],
      "ios": ["cloud", "device"],
      "iosSwift": ["cloud"],
      "web": ["cloud", "device"],
      "unity": ["cloud"],
      "amp": ["cloud"],
      "reactnative": ["cloud"],
      "flutter": ["cloud"],
      "cordova": ["cloud"],
      "shopify": ["cloud"],
      "cloud": ["cloud"],
      "warehouse": ["cloud"]
    },
    "supportedMessageTypes": {
      "cloud": ["track", "identify"],
      "device": {
        "web": ["identify", "track", "page"],
        "android": ["identify", "track", "screen"],
        "ios": ["identify", "track", "screen"]
      }
    },
    "destConfig": {
      "defaultConfig": [
        "apiKey",
        "fs_org",
        "blacklistedEvents",
        "whitelistedEvents",
        "eventFilteringOption"
      ],
      "web": [
        "useNativeSDK",
        "connectionMode",
        "fs_debug_mode",
        "fs_host",
        "consentManagement",
        "oneTrustCookieCategories",
        "ketchConsentPurposes"
      ],
      "android": [
        "useNativeSDK",
        "connectionMode",
        "consentManagement",
        "oneTrustCookieCategories",
        "ketchConsentPurposes"
      ],
      "androidKotlin": ["connectionMode", "consentManagement"],
      "ios": [
        "useNativeSDK",
        "connectionMode",
        "consentManagement",
        "oneTrustCookieCategories",
        "ketchConsentPurposes"
      ],
      "iosSwift": ["connectionMode", "consentManagement"],
      "unity": [
        "connectionMode",
        "consentManagement",
        "oneTrustCookieCategories",
        "ketchConsentPurposes"
      ],
      "amp": [
        "connectionMode",
        "consentManagement",
        "oneTrustCookieCategories",
        "ketchConsentPurposes"
      ],
      "cloud": [
        "connectionMode",
        "consentManagement",
        "oneTrustCookieCategories",
        "ketchConsentPurposes"
      ],
      "warehouse": [
        "connectionMode",
        "consentManagement",
        "oneTrustCookieCategories",
        "ketchConsentPurposes"
      ],
      "reactnative": [
        "connectionMode",
        "consentManagement",
        "oneTrustCookieCategories",
        "ketchConsentPurposes"
      ],
      "flutter": [
        "connectionMode",
        "consentManagement",
        "oneTrustCookieCategories",
        "ketchConsentPurposes"
      ],
      "cordova": [
        "connectionMode",
        "consentManagement",
        "oneTrustCookieCategories",
        "ketchConsentPurposes"
      ],
      "shopify": [
        "connectionMode",
        "consentManagement",
        "oneTrustCookieCategories",
        "ketchConsentPurposes"
      ]
    },
    "secretKeys": ["apiKey"]
  }
}
