{
  "uiConfig": [
    {
      "title": "Connection Settings",
      "fields": [
        {
          "type": "textInput",
          "label": "Attribution Project Key",
          "value": "writeKey",
          "regex": "^(.{1,100})$",
          "regexErrorMessage": "Invalid Attribution Project Key",
          "required": true,
          "placeholder": "e.g: AGzXXK9cBV"
        }
      ]
    },
    {
      "title": "Consent Settings",
      "fields": [
        {
          "type": "dynamicCustomForm",
          "value": "oneTrustCookieCategories",
          "label": "OneTrust Cookie Categories",
          "customFields": [
            {
              "type": "textInput",
              "placeholder": "Marketing",
              "value": "oneTrustCookieCategory",
              "label": "Category Name/ID",
              "required": false
            }
          ]
        }
      ]
    }
  ]
}
