{
  "name": "OLARK",
  "displayName": "Olark",
  "config": {
    "transformAt": "processor",
    "transformAtV1": "processor",
    "saveDestinationResponse": true,
    "includeKeys": [
      "siteId",
      "groupId",
      "recordLiveChatEvents",
      "updateEventNames",
      "standardToEvent",
      "eventFilteringOption",
      "blacklistedEvents",
      "whitelistedEvents"
    ],
    "excludeKeys": [],
    "supportedSourceTypes": ["web"],
    "supportedMessageTypes": ["identify"],
    "destConfig": {
      "defaultConfig": [
        "siteId",
        "groupId",
        "recordLiveChatEvents",
        "updateEventNames",
        "standardToEvent",
        "eventFilteringOption",
        "blacklistedEvents",
        "whitelistedEvents"
      ],
      "web": ["useNativeSDK", "oneTrustCookieCategories"]
    }
  }
}
