{
  "name": "TIKTOK_ADS",
  "displayName": "TikTok Ads",
  "config": {
    "transformAtV1": "router",
    "saveDestinationResponse": true,
    "includeKeys": [
      "pixelCode",
      "sendCustomEvents",
      "hashUserProperties",
      "eventsToStandard",
      "blacklistedEvents",
      "whitelistedEvents",
      "eventFilteringOption",
      "oneTrustCookieCategories",
      "ketchConsentPurposes"
    ],
    "excludeKeys": [],
    "supportedSourceTypes": ["web", "cloud", "ios", "android"],
    "supportedMessageTypes": {
      "cloud": ["track"],
      "device": {
        "web": ["identify", "track", "page"],
        "ios": ["identify", "track", "page"],
        "android": ["identify", "track", "page"]
      }
    },
    "supportedConnectionModes": {
      "web": ["cloud", "device"],
      "android": ["cloud"],
      "ios": ["cloud"]
    },
    "destConfig": {
      "defaultConfig": [
        "sendCustomEvents",
        "accessToken",
        "version",
        "pixelCode",
        "hashUserProperties",
        "eventsToStandard",
        "blacklistedEvents",
        "whitelistedEvents",
        "eventFilteringOption",
        "oneTrustCookieCategories",
        "ketchConsentPurposes"
      ],
      "web": ["useNativeSDK"]
    },
    "secretKeys": ["accessToken", "pixelCode"]
  }
}
