{
  "name": "SPOTIFYPIXEL",
  "displayName": "Spotify Pixel",
  "config": {
    "transformAtV1": "processor",
    "saveDestinationResponse": true,
    "includeKeys": [
      "pixelId",
      "eventsToSpotifyPixelEvents",
      "blacklistedEvents",
      "whitelistedEvents",
      "oneTrustCookieCategories",
      "eventFilteringOption",
      "enableAliasCall",
      "consentManagement",
      "ketchConsentPurposes"
    ],
    "excludeKeys": [],
    "supportedSourceTypes": ["web"],
    "supportedMessageTypes": {
      "device": {
        "web": ["track", "page"]
      }
    },
    "supportedConnectionModes": {
      "web": ["device"]
    },
    "destConfig": {
      "defaultConfig": [
        "pixelId",
        "eventsToSpotifyPixelEvents",
        "blacklistedEvents",
        "whitelistedEvents",
        "eventFilteringOption",
        "enableAliasCall"
      ],
      "web": [
        "useNativeSDK",
        "connectionMode",
        "consentManagement",
        "oneTrustCookieCategories",
        "ketchConsentPurposes"
      ]
    },
    "secretKeys": []
  }
}
