[
  {
    "fields": [
      {
        "label": "MinIO Endpoint",
        "placeholder": "e.g: play.min.io:9000",
        "regex": "^(.{0,100})$",
        "regexErrorMessage": "Invalid MinIO Endpoint",
        "required": true,
        "type": "textInput",
        "value": "endPoint"
      },
      {
        "label": "MinIO Access Key ID",
        "placeholder": "e.g: Q3AM3UQ867SPQQA43P2F",
        "regex": "^(.{0,100})$",
        "regexErrorMessage": "Invalid MinIO Access Key ID",
        "required": true,
        "secret": true,
        "type": "textInput",
        "value": "accessKeyID"
      },
      {
        "label": "MinIO Secret Access Key",
        "placeholder": "e.g: zuf+tfteSlswRu7BJ86wekitnifILbZam1KYY3TG",
        "regex": "^(.{0,100})$",
        "regexErrorMessage": "Invalid MinIO Secret Access Key",
        "required": true,
        "secret": true,
        "type": "textInput",
        "value": "secretAccessKey"
      },
      {
        "label": "MINIO Bucket Name",
        "placeholder": "e.g: minio-event-logs",
        "regex": "^(.{0,100})$",
        "regexErrorMessage": "Invalid MINIO Bucket Name",
        "required": true,
        "type": "textInput",
        "value": "bucketName"
      },
      {
        "label": "Prefix",
        "placeholder": "e.g: rudder",
        "regex": "^(.{0,100})$",
        "regexErrorMessage": "Invalid Prefix",
        "required": false,
        "type": "textInput",
        "value": "prefix"
      },
      {
        "default": true,
        "label": "Use SSL for connection",
        "type": "checkbox",
        "value": "useSSL"
      }
    ],
    "title": "1. Connection Settings"
  }
]