{
  "config": {
    "destConfig": {
      "defaultConfig": [
        "advId",
        "pixId",
        "eventsMap",
        "blacklistedEvents",
        "whitelistedEvents",
        "eventFilteringOption"
      ],
      "web": [
        "useNativeSDK",
        "oneTrustCookieCategories"
      ]
    },
    "excludeKeys": [],
    "includeKeys": [
      "advId",
      "pixId",
      "eventsMap",
      "blacklistedEvents",
      "whitelistedEvents",
      "oneTrustCookieCategories",
      "eventFilteringOption"
    ],
    "saveDestinationResponse": true,
    "secretKeys": [],
    "supportedMessageTypes": [
      "identify",
      "track",
      "page"
    ],
    "supportedSourceTypes": [
      "web"
    ],
    "transformAt": "processor",
    "transformAtV1": "processor"
  },
  "displayName": "Adroll",
  "name": "ADROLL",
  "options": {
    "isBeta": true
  }
}