{
  "config": {
    "destConfig": {
      "defaultConfig": [
        "address",
        "database",
        "password",
        "prefix",
        "secure",
        "skipVerify",
        "caCertificate",
        "clusterMode"
      ]
    },
    "excludeKeys": [],
    "includeKeys": [],
    "saveDestinationResponse": true,
    "secretKeys": [
      "password",
      "caCertificate"
    ],
    "supportedMessageTypes": [
      "identify"
    ],
    "supportedSourceTypes": [
      "android",
      "ios",
      "web",
      "unity",
      "amp",
      "cloud",
      "warehouse",
      "reactnative",
      "flutter",
      "cordova"
    ],
    "transformAt": "processor",
    "transformAtV1": "processor"
  },
  "displayName": "Redis",
  "name": "REDIS"
}