{
  "config": {
    "destConfig": {
      "defaultConfig": [
        "accountId",
        "blacklistedEvents",
        "whitelistedEvents",
        "eventFilteringOption"
      ],
      "web": [
        "useNativeSDK",
        "oneTrustCookieCategories"
      ]
    },
    "excludeKeys": [],
    "includeKeys": [
      "accountId",
      "blacklistedEvents",
      "whitelistedEvents",
      "oneTrustCookieCategories",
      "eventFilteringOption"
    ],
    "saveDestinationResponse": true,
    "secretKeys": [],
    "supportedMessageTypes": [
      "identify",
      "page",
      "screen",
      "track"
    ],
    "supportedSourceTypes": [
      "android",
      "ios",
      "web",
      "unity",
      "amp",
      "cloud",
      "warehouse",
      "reactnative",
      "flutter",
      "cordova"
    ],
    "transformAt": "processor",
    "transformAtV1": "processor"
  },
  "displayName": "Appcues",
  "name": "APPCUES"
}