{
  "uiConfig": [
    {
      "fields": [
        {
          "footerNote": "Your Marketo Accound ID from Admin settings section",
          "label": "Munchkin Account Id",
          "placeholder": "e.g: 585-AXP-446",
          "regex": "^(.{0,100})$",
          "regexErrorMessage": "Invalid Munchkin Account Id",
          "required": true,
          "type": "textInput",
          "value": "accountId"
        },
        {
          "footerNote": "Your REST API Client ID",
          "label": "Client ID",
          "placeholder": "e.g: 53b1934e-51dd-4599-b24b-92612c71515f",
          "regex": "^(.{0,100})$",
          "regexErrorMessage": "Invalid Client ID",
          "required": true,
          "type": "textInput",
          "value": "clientId"
        },
        {
          "footerNote": "Your REST API Client Secret",
          "label": "Client Secret",
          "placeholder": "e.g: oxzXtNhcuw9YGsdhplKUeEMi8765dsfw",
          "regex": "^(.{0,100})$",
          "regexErrorMessage": "Invalid Client Secret",
          "required": true,
          "secret": true,
          "type": "textInput",
          "value": "clientSecret"
        }
      ],
      "title": "Connection Settings"
    },
    {
      "fields": [
        {
          "default": false,
          "footerNote": "If turned on, you need to send userId with every track call",
          "label": "Track anonymous events",
          "type": "checkbox",
          "value": "trackAnonymousEvents"
        },
        {
          "default": true,
          "footerNote": "If turned on, we will create a new lead if the user is not present",
          "label": "Create Lead if it does not exist",
          "type": "checkbox",
          "value": "createIfNotExist"
        },
        {
          "footerNote": "You can find the Activity ID in your Admin section under Custom Activity on your Marketo dashboard",
          "keyLeft": "from",
          "keyRight": "to",
          "label": "Map events to Marketo Activity ID",
          "labelLeft": "Event Name",
          "labelRight": "Activity ID",
          "placeholderLeft": "e.g: Product Clicked",
          "placeholderRight": "e.g: 100001",
          "type": "dynamicForm",
          "value": "customActivityEventMap"
        },
        {
          "footerNote": "We'll convert the data type based on the property value",
          "keyLeft": "from",
          "keyRight": "to",
          "label": "Map event properties to Marketo property name",
          "labelLeft": "Event Property name",
          "labelRight": "Marketo Property name",
          "placeholderLeft": "e.g: name",
          "placeholderRight": "e.g: productName",
          "type": "dynamicForm",
          "value": "customActivityPropertyMap"
        },
        {
          "footerNote": "Create a map between your event name and your event proerty names where the property on the right hand side is your primary key in Marketo",
          "keyLeft": "from",
          "keyRight": "to",
          "label": "Map event name to Marketo primary key",
          "labelLeft": "Event name",
          "labelRight": "Marketo Property name",
          "placeholderLeft": "e.g: Product Clicked",
          "placeholderRight": "e.g: name",
          "type": "dynamicForm",
          "value": "customActivityPrimaryKeyMap"
        }
      ],
      "title": "Custom Activity Settings"
    },
    {
      "fields": [
        {
          "footerNote": "We map spec'd traits for you. Add the extra fields here",
          "keyLeft": "from",
          "keyRight": "to",
          "label": "Map your traits to Marketo custom fields",
          "labelLeft": "Traits name",
          "labelRight": "Custom field name",
          "placeholderLeft": "e.g: leadScore",
          "placeholderRight": "e.g: customLeadScore",
          "type": "dynamicForm",
          "value": "leadTraitMapping"
        }
      ],
      "title": "Lead Mapping"
    }
  ]
}