{
  "uiConfig": [
    {
      "title": "Connection Settings",
      "fields": [
        {
          "type": "textInput",
          "label": "API Key",
          "value": "apiKey",
          "regex": ".*",
          "required": true,
          "placeholder": "e.g: FXLXXXEhGJyvmZ4",
          "secret": true
        }
      ]
    },
    {
      "title": "Consent Settings",
      "fields": [
        {
          "type": "dynamicCustomForm",
          "value": "oneTrustCookieCategories",
          "label": "OneTrust Cookie Categories",
          "customFields": [
            {
              "type": "textInput",
              "placeholder": "Marketing",
              "value": "oneTrustCookieCategory",
              "label": "Category Name/ID",
              "required": false
            }
          ]
        }
      ]
    }
  ]
}
