{
  "name": "INTERCOM",
  "displayName": "Intercom",
  "config": {
    "cdkV2Enabled": true,
    "supportsVisualMapper": true,
    "transformAtV1": "router",
    "saveDestinationResponse": true,
    "isAudienceSupported": true,
    "includeKeys": [
      "appId",
      "mobileApiKeyAndroid",
      "mobileApiKeyIOS",
      "blacklistedEvents",
      "whitelistedEvents",
      "oneTrustCookieCategories",
      "eventFilteringOption"
    ],
    "excludeKeys": [],
    "supportedSourceTypes": [
      "android",
      "ios",
      "web",
      "unity",
      "amp",
      "cloud",
      "warehouse",
      "reactnative",
      "flutter",
      "cordova",
      "shopify"
    ],
    "supportedMessageTypes": {
      "cloud": ["identify", "track", "group"],
      "device": {
        "web": ["identify", "track", "page"],
        "android": ["identify", "track"],
        "ios": ["identify", "track"]
      }
    },
    "supportedConnectionModes": {
      "web": ["cloud", "device"],
      "android": ["cloud", "device"],
      "ios": ["cloud", "device"],
      "unity": ["cloud"],
      "amp": ["cloud"],
      "reactnative": ["cloud"],
      "flutter": ["cloud"],
      "cordova": ["cloud"],
      "shopify": ["cloud"]
    },
    "destConfig": {
      "defaultConfig": [
        "appId",
        "apiKey",
        "apiServer",
        "sendAnonymousId",
        "mobileApiKeyIOS",
        "blacklistedEvents",
        "whitelistedEvents",
        "mobileApiKeyAndroid",
        "eventFilteringOption",
        "oneTrustCookieCategories"
      ],
      "android": ["useNativeSDK", "mobileApiKeyAndroid", "connectionMode"],
      "ios": ["useNativeSDK", "mobileApiKeyIOS", "connectionMode"],
      "web": ["useNativeSDK", "appId", "connectionMode"]
    },
    "secretKeys": []
  }
}
