{
  "config": {
    "destConfig": {
      "defaultConfig": [
        "apiKey",
        "signUpSourceId"
      ]
    },
    "excludeKeys": [],
    "includeKeys": [],
    "saveDestinationResponse": true,
    "secretKeys": [
      "apiKey"
    ],
    "supportedMessageTypes": [
      "identify",
      "track"
    ],
    "supportedSourceTypes": [
      "android",
      "ios",
      "web",
      "unity",
      "amp",
      "cloud",
      "warehouse",
      "reactnative",
      "flutter",
      "cordova"
    ],
    "transformAt": "processor",
    "transformAtV1": "processor"
  },
  "displayName": "Attentive Tag",
  "name": "ATTENTIVE_TAG"
}